mcp_server_c8y/__init__.py
mcp_server_c8y/formatters.py
mcp_server_c8y/logging_setup.py
mcp_server_c8y/openapi.py
mcp_server_c8y/server.py
mcp_server_c8y/settings.py
mcp_server_c8y/utils.py
mcp_server_c8y-0.1.17.dist-info/METADATA
mcp_server_c8y-0.1.17.dist-info/WHEEL
mcp_server_c8y-0.1.17.dist-info/entry_points.txt
mcp_server_c8y-0.1.17.dist-info/licenses/LICENSE
mcp_server_c8y-0.1.17.dist-info/RECORD
