Metadata-Version: 2.4
Name: mcp_server_c8y
Version: 0.1.17
Summary: A Python-based MCP server for Cumulocity IoT platform integration
Author: Cumulocity
License: Apache-2.0
License-File: LICENSE
Keywords: alarms,cumulocity,device-management,iot,mcp,measurements
Classifier: Development Status :: 4 - Beta
Classifier: Intended Audience :: Developers
Classifier: License :: OSI Approved :: Apache Software License
Classifier: Programming Language :: Python :: 3
Classifier: Programming Language :: Python :: 3.10
Classifier: Programming Language :: Python :: 3.11
Classifier: Programming Language :: Python :: 3.12
Classifier: Topic :: Software Development :: Libraries :: Python Modules
Requires-Python: >=3.10
Requires-Dist: c8y-api>=3.2.1
Requires-Dist: click>=8.0.0
Requires-Dist: fastmcp>=2.8.0
Requires-Dist: httpx>=0.28.1
Requires-Dist: pydantic>=2.0.0
Requires-Dist: python-dotenv>=1.0.0
Requires-Dist: tabulate>=0.9.0
